<?xml version="1.0" encoding="utf-8"?>
<LanguageData>

  <!-- 調味料 -->

  <R_Syrup.label>米糖</R_Syrup.label>
  <R_Syrup.description>傳統的甜味料，在砂糖普及前的日本到處都可以見到。 \n米糖，就像是玉米糖漿是由玉米澱粉中提煉獲得那樣，它是一種由大米澱粉中提煉而來的葡萄糖漿。</R_Syrup.description>

  <R_NaturalSalt.label>天然鹽</R_NaturalSalt.label>
  <R_NaturalSalt.description>含鹽的水蒸餾出來的鹽。 \n一種鹹味的晶體，也是料理中不可或缺的調味品。</R_NaturalSalt.description>

  <R_VinegarBarrel.label>米醋桶</R_VinegarBarrel.label>
  <R_VinegarBarrel.description>一個裝滿米醋原料的桶，還需要經過發酵才可以得到米醋。</R_VinegarBarrel.description>

  <R_Vinegar.label>米醋</R_Vinegar.label>
  <R_Vinegar.description>料理時用得到的醋。 \n據現有文字記載，東方醋起源於中國，有文獻記載的釀醋歷史至少也在三千年以上。“醋”在古中國寫作“酢”，所以在日本也寫作“酢”。</R_Vinegar.description>

  <R_SoySauceBarrel.label>醬油桶</R_SoySauceBarrel.label>
  <R_SoySauceBarrel.description>一個裝滿醬油原料的桶，還需要經過發酵才可以得到醬油。</R_SoySauceBarrel.description>

  <R_SoySauce.label>醬油</R_SoySauce.label>
  <R_SoySauce.description>料理時用得到的醬油，是起源於中國的傳統的調味品。 \n用豆、麥、麩皮釀造的液體調味品。色澤紅褐色，有獨特醬香，滋味鮮美，有助於促進食慾。</R_SoySauce.description>

  <R_MisoBarrel.label>味噌桶</R_MisoBarrel.label>
  <R_MisoBarrel.description>一個裝滿味噌原料的桶，還需要經過發酵才可以得到味噌。</R_MisoBarrel.description>

  <R_Miso.label>味噌</R_Miso.label>
  <R_Miso.description>又稱面豉醬，是以黃豆為主原料，加入鹽及不同的種麴發酵而成。 \n在日本，味噌是最受歡迎的調味品，它既可以做成湯品，又能與肉類烹煮成菜，還能做成火鍋的湯底，既美味又健康呢。</R_Miso.description>

  <ZP_Spice.label>香辛料</ZP_Spice.label>
  <ZP_Spice.description>用於改善料理風味的香辛料。</ZP_Spice.description>


</LanguageData>